{"traffic": {"KP0018": [{"id": "date", "min": [2014, 5, 1]}, {"id": "co", "yAxis": 0, "color": "#871455", "data": [3.351, 3.63, 68.556, 71.277, 64.269, 82.431, 81.059, 82.278, 79.695, 86.615, 81.917, 71.76, 83.713, 82.481, 84.321, 81.789, 75.613, 74.064, 92.441, 72.069, 68.922, 82.205, 83.203, 90.588, 77.907, 90.633, 83.949, 89.128, 83.942, 94.33, 86.421, 61.952, 86.862, 100.55, 92.52, 90.158, 91.41, 91.466, 67.719, 87.618, 91.374, 79.899, 79.638, 81.053, 94.433, 93.837, 79.273, 92.407, 95.461, 90.708, 59.972, 86.911, 55.21, 81.262, 90.493, 89.22, 85.048, 94.859, 102.108, 84.981, 88.25, 100.62, 98.271, 86.787, 95.094, 96.74, 87.387, 99.968, 98.186, 69.055, 58.499, 91.771, 84.4, 70.339, 73.814, 84.468, 88.867, 104.119, 97.596, 82.966, 103.233, 105.474, 105.615, 83.655, 97.535, 87.995, 79.34]}, {"id": "cap", "yAxis": 0, "color": "#FFBE4B", "data": [95.0, 95.0, 95.0, 95.0, 95.0, 95.0, 95.0, 95.0, 95.0, 95.0, 95.0, 95.0, 95.0, 95.0, 95.0, 95.0, 95.0, 95.0, 95.0, 95.0, 95.0, 95.0, 95.0, 95.0, 95.0, 95.0, 90.225, 95.0, 95.0, 95.0, 95.0, 95.0, 95.0, 95.0, 95.0, 95.0, 95.0, 95.0, 95.0, 95.0, 95.0, 95.0, 95.0, 95.0, 95.0, 95.0, 95.0, 95.0, 95.0, 95.0, 95.0, 95.0, 95.0, 95.0, 95.0, 95.0, 95.0, 95.0, 95.0, 95.0, 95.0, 95.0, 95.0, 95.0, 95.0, 95.0, 95.0, 95.0, 95.0, 95.0, 95.0, 95.0, 95.0, 95.0, 95.0, 95.0, 95.0, 95.0, 95.0, 95.0, 95.0, 95.0, 95.0, 95.0, 95.0, 95.0, 95.0]}], "KP0034": [{"id": "date", "min": [2014, 5, 1]}, {"id": "rp", "yAxis": 0, "color": "#FF821E", "data": [0.092]}], "KP0043": [{"id": "date", "min": [2014, 5, 1]}, {"id": "rp", "yAxis": 0, "color": "#FF821E", "data": [0.009, null, null, null, null, 554.999, null, null, null, null, null, null, null, null, null, null, null, 0.096, null, null, null, null, null, null, null, null, null, null, null, 2.967, null, null, null, null, null, null, null, 1.278, null, null, null, null]}, {"id": "cap", "yAxis": 0, "color": "#FFBE4B", "data": [76.0, 76.0, 76.0, 76.0, 76.0, 76.0, 76.0, 76.0, 76.0, 76.0, 76.0, 76.0, 76.0, 76.0, 76.0, 76.0, 76.0, 76.0, 76.0, 76.0, 76.0, 76.0, 76.0, 76.0, 76.0, 76.0, 76.0, 76.0, 76.0, 76.0, 76.0, 76.0, 76.0, 76.0, 76.0, 76.0, 76.0, 76.0, 76.0, 76.0, null, 76.0]}]}, "meta": {"companyName": "Cochin", "units": "Mb/d", "frequency": "m", "defaultPoint": "KP0018", "build": true, "trendText": {"KP0034": [{"throughChange": {"pct": 0, "from": 0.092, "to": 0.092}, "fromDate": [2014, 9], "toDate": [2014, 9], "name": "default"}], "KP0043": [{"throughChange": {"pct": -100, "from": 0.426, "to": 0.0}, "fromDate": [2017, 9], "toDate": [2017, 12], "name": "default"}], "KP0018": [{"throughChange": {"pct": -10, "from": 98.248, "to": 88.29}, "fromDate": [2021, 6], "toDate": [2021, 9], "name": "default"}]}, "directions": {"KP0018": ["w"], "KP0034": ["e"], "KP0043": ["e"]}, "keyPoints": [{"KeyPointID": "KP0018", "loc": [53.75, -113.17]}]}}