{"meta": {"companyName": "Alliance", "first_year": 2019, "current_year": 2024, "total_events": 47, "ground_disturbance_count": 18, "damage_count": 0, "further_action_required": 1, "build": true}, "events": [{"id": "UX2019-056", "et": ["c"], "wpd": "ns", "wgd": "n", "y": 2019, "bc": [null], "wdi": "ns", "mod": "ns", "loc": [54.41, -117.14]}, {"id": "UX2019-134", "et": ["v"], "wpd": "ns", "wgd": "n", "y": 2019, "bc": [null], "wdi": "ns", "mod": "ns", "loc": [49.09, -101.83]}, {"id": "UX2019-034", "et": ["v"], "wpd": "ns", "wgd": "n", "y": 2019, "bc": [null], "wdi": "ns", "mod": "ns", "loc": [53.99, -115.29]}, {"id": "UX2019-015", "et": ["g", "v"], "wpd": "ns", "wgd": "y", "y": 2019, "bc": [null], "wdi": "ns", "mod": "ns", "loc": [54.37, -116.83]}, {"id": "UX2019-249", "et": ["g"], "wpd": "ns", "wgd": "y", "y": 2019, "bc": [null], "wdi": "ns", "mod": "ns", "loc": [55.29, -119.22]}, {"id": "UX2019-248", "et": ["g"], "wpd": "ns", "wgd": "y", "y": 2019, "bc": [null], "wdi": "ns", "mod": "ns", "loc": [55.37, -119.15]}, {"id": "UX2019-012", "et": ["v"], "wpd": "ns", "wgd": "n", "y": 2019, "bc": [null], "wdi": "ns", "mod": "ns", "loc": [54.09, -116.62]}, {"id": "UX2019-053", "et": ["v"], "wpd": "ns", "wgd": "n", "y": 2019, "bc": [null], "wdi": "ns", "mod": "ns", "loc": [50.33, -104.61]}, {"id": "UX2019-166", "et": ["g", "v"], "wpd": "ns", "wgd": "y", "y": 2019, "bc": [null], "wdi": "ns", "mod": "ns", "loc": [50.65, -105.31]}, {"id": "UX2019-010", "et": ["v"], "wpd": "ns", "wgd": "n", "y": 2019, "bc": [null], "wdi": "ns", "mod": "ns", "loc": [54.38, -116.78]}, {"id": "UX2019-003", "et": ["c", "g"], "wpd": "ns", "wgd": "y", "y": 2019, "bc": [null], "wdi": "ns", "mod": "ns", "loc": [59.95, -121.92]}, {"id": "UX2020-236", "et": ["g", "v"], "wpd": "ns", "wgd": "y", "y": 2020, "bc": [null], "wdi": "ns", "mod": "ns", "loc": [49.08, -101.81]}, {"id": "UX2020-164", "et": ["g", "v"], "wpd": "ns", "wgd": "y", "y": 2020, "bc": [null], "wdi": "ns", "mod": "ns", "loc": [49.35, -102.35]}, {"id": "UX2020-021", "et": ["v"], "wpd": "ns", "wgd": "n", "y": 2020, "bc": [null], "wdi": "ns", "mod": "ns", "loc": [50.38, -104.71]}, {"id": "UX2020-010", "et": ["g", "v"], "wpd": "ns", "wgd": "y", "y": 2020, "bc": [null], "wdi": "ns", "mod": "ns", "loc": [54.19, -116.22]}, {"id": "UX2020-180", "et": ["g"], "wpd": "ns", "wgd": "y", "y": 2020, "bc": [null], "wdi": "ns", "mod": "ns", "loc": [55.1, -119.42]}, {"id": "DPR2020-004", "et": ["v"], "wpd": "ns", "wgd": "n", "y": 2020, "bc": ["21713", "21779", "21823", "21713", "21779", "21825"], "wdi": "1", "mod": "s", "loc": [54.39, -116.78]}, {"id": "UX2020-122", "et": ["g"], "wpd": "ns", "wgd": "y", "y": 2020, "bc": [null], "wdi": "ns", "mod": "ns", "loc": [50.65, -105.31]}, {"id": "DPR2021-129", "et": ["c", "g"], "wpd": "ns", "wgd": "y", "y": 2021, "bc": ["21713", "21779", "21823", "21713", "21779", "21826"], "wdi": "3", "mod": "ns", "loc": [51.31, -106.86]}, {"id": "DPR2021-167", "et": ["g"], "wpd": "ns", "wgd": "y", "y": 2021, "bc": ["21713", "21779", "21825"], "wdi": "1", "mod": "s", "loc": [55.09, -119.25]}, {"id": "DPR2021-298", "et": ["d"], "wpd": "n", "wgd": "n", "y": 2021, "bc": ["21713", "21776", "21792"], "wdi": "1", "mod": "o", "loc": [49.32, -102.3]}, {"id": "DPR2021-099", "et": ["v"], "wpd": "ns", "wgd": "n", "y": 2021, "bc": ["21713", "21779", "21826"], "wdi": "1", "mod": "a", "loc": [54.08, -115.43]}, {"id": "DPR2021-157", "et": ["c"], "wpd": "ns", "wgd": "n", "y": 2021, "bc": ["21713", "21779", "21823"], "wdi": "1", "mod": "g", "loc": [53.38, -116.2]}, {"id": "DPR2021-310", "et": ["c"], "wpd": "ns", "wgd": "n", "y": 2021, "bc": ["21713", "21779", "21824"], "wdi": "1", "mod": "g", "loc": [54.49, -116.79]}, {"id": "DPR2021-311", "et": ["v"], "wpd": "ns", "wgd": "n", "y": 2021, "bc": ["21713", "21779", "21823"], "wdi": "1", "mod": "g", "loc": [54.68, -118.34]}, {"id": "DPR2021-002", "et": ["d"], "wpd": "n", "wgd": "n", "y": 2021, "bc": ["21713", "21779", "21823"], "wdi": "2", "mod": "o", "loc": [54.14, -117.24]}, {"id": "DPR2021-222", "et": ["v"], "wpd": "ns", "wgd": "n", "y": 2021, "bc": ["21713", "21779", "21819"], "wdi": "1", "mod": "s", "loc": [53.52, -116.5]}, {"id": "DPR2021-019", "et": ["v"], "wpd": "ns", "wgd": "n", "y": 2021, "bc": ["21713", "21775", "21784", "21786"], "wdi": "1", "mod": "s", "loc": [54.19, -115.84]}, {"id": "DPR2021-290", "et": ["g"], "wpd": "ns", "wgd": "y", "y": 2021, "bc": ["21713", "21779", "21823"], "wdi": "3", "mod": "ns", "loc": [54.83, -118.63]}, {"id": "DPR2021-139", "et": ["g"], "wpd": "ns", "wgd": "y", "y": 2021, "bc": ["21713", "21779", "21825"], "wdi": "2", "mod": "a", "loc": [55.82, -119.47]}, {"id": "DPR2022-178", "et": ["c", "g", "v"], "wpd": "ns", "wgd": "y", "y": 2022, "bc": ["21713", "21775", "21784", "21786"], "wdi": "1", "mod": "s", "loc": [53.77, -113.07]}, {"id": "DPR2022-223", "et": ["v"], "wpd": "ns", "wgd": "n", "y": 2022, "bc": ["21713", "21779", "21823", "21713", "21779", "21826"], "wdi": "1", "mod": "s", "loc": [54.13, -115.54]}, {"id": "DPR2022-202", "et": ["c"], "wpd": "ns", "wgd": "n", "y": 2022, "bc": ["21713", "21779", "21823", "21713", "21779", "21826"], "wdi": "1", "mod": "s", "loc": [51.21, -106.6]}, {"id": "DPR2022-070", "et": ["c"], "wpd": "ns", "wgd": "n", "y": 2022, "bc": ["21713", "21775", "21784", "21786"], "wdi": "1", "mod": "s", "loc": [49.32, -102.3]}, {"id": "DPR2022-032", "et": ["v"], "wpd": "ns", "wgd": "n", "y": 2022, "bc": ["21713", "21779", "21823"], "wdi": "1", "mod": "g", "loc": [52.07, -109.41]}, {"id": "DPR2023-207", "et": ["c"], "wpd": "ns", "wgd": "n", "y": 2023, "bc": ["21903", "21712", "21752", "21761"], "wdi": "1", "mod": "s", "loc": [54.96, -119.19]}, {"id": "DPR2023-285", "et": ["v"], "wpd": "ns", "wgd": "n", "y": 2023, "bc": ["21713", "21779", "21823", "21713", "21779", "21826"], "wdi": "2", "mod": "a", "loc": [55.36, -119.5]}, {"id": "DPR2023-189", "et": ["c"], "wpd": "ns", "wgd": "n", "y": 2023, "bc": ["21713", "21779", "21823", "21713", "21779", "21826"], "wdi": "3", "mod": "ns", "loc": [55.37, -118.51]}, {"id": "DPR2023-252", "et": ["v"], "wpd": "ns", "wgd": "n", "y": 2023, "bc": ["21713", "21779", "21823", "21713", "21779", "21826"], "wdi": "3", "mod": "ns", "loc": [54.02, -115.33]}, {"id": "DPR2023-223", "et": ["c", "v"], "wpd": "ns", "wgd": "n", "y": 2023, "bc": ["21713", "21780", "21830"], "wdi": "1", "mod": "g", "loc": [49.31, -102.28]}, {"id": "DPR2023-070", "et": ["c"], "wpd": "ns", "wgd": "n", "y": 2023, "bc": ["21713", "21779", "21823", "21713", "21779", "21826"], "wdi": "1", "mod": "s", "loc": [54.48, -116.79]}, {"id": "DPR2023-051", "et": ["c", "g"], "wpd": "ns", "wgd": "y", "y": 2023, "bc": ["21903", "21712", "21752", "21754"], "wdi": "3", "mod": "ns", "loc": [55.36, -119.02]}, {"id": "DPR2023-145", "et": ["c", "v"], "wpd": "ns", "wgd": "n", "y": 2023, "bc": ["21713", "21776", "21792"], "wdi": "1", "mod": "s", "loc": [54.04, -115.37]}, {"id": "DPR2023-036", "et": ["g"], "wpd": "ns", "wgd": "y", "y": 2023, "bc": ["21713", "21776", "21792"], "wdi": "2", "mod": "a", "loc": [54.36, -117.21]}, {"id": "DPR2023-006", "et": ["d"], "wpd": "n", "wgd": "n", "y": 2023, "bc": ["21713", "21776", "21792"], "wdi": "1", "mod": "o", "loc": [55.86, -119.59]}, {"id": "DPR2023-005", "et": ["g"], "wpd": "ns", "wgd": "y", "y": 2023, "bc": ["21713", "21779", "21823"], "wdi": "3", "mod": "s", "loc": [55.09, -119.21]}, {"id": "DPR2023-248", "et": ["c", "v"], "wpd": "ns", "wgd": "n", "y": 2023, "bc": ["21713", "21779", "21823", "21713", "21779", "21826"], "wdi": "2", "mod": "a", "loc": [55.35, -119.4]}]}