{"meta": {"companyName": "Cochin", "first_year": 2019, "current_year": 2024, "total_events": 12, "ground_disturbance_count": 8, "damage_count": 0, "further_action_required": 0, "build": true}, "events": [{"id": "UX2019-167", "et": ["g"], "wpd": "ns", "wgd": "y", "y": 2019, "bc": [null], "wdi": "ns", "mod": "ns", "loc": [50.65, -105.31]}, {"id": "UX2019-235", "et": ["c", "g"], "wpd": "ns", "wgd": "y", "y": 2019, "bc": [null], "wdi": "ns", "mod": "ns", "loc": [53.74, -112.95]}, {"id": "UX2020-123", "et": ["v"], "wpd": "ns", "wgd": "n", "y": 2020, "bc": [null], "wdi": "ns", "mod": "ns", "loc": [50.65, -105.31]}, {"id": "UX2020-160", "et": ["c", "g"], "wpd": "ns", "wgd": "y", "y": 2020, "bc": [null], "wdi": "ns", "mod": "ns", "loc": [52.49, -110.2]}, {"id": "UX2020-246", "et": ["g"], "wpd": "ns", "wgd": "y", "y": 2020, "bc": [null], "wdi": "ns", "mod": "ns", "loc": [53.33, -111.84]}, {"id": "UX2020-268", "et": ["g"], "wpd": "ns", "wgd": "y", "y": 2020, "bc": [null], "wdi": "ns", "mod": "ns", "loc": [50.59, -105.15]}, {"id": "DPR2021-216", "et": ["g", "v"], "wpd": "ns", "wgd": "y", "y": 2021, "bc": ["21713", "21779", "21825", "21713", "21779", "21826"], "wdi": "2", "mod": "a", "loc": [53.74, -112.89]}, {"id": "DPR2022-069", "et": ["v"], "wpd": "ns", "wgd": "n", "y": 2022, "bc": ["21903", "21712", "21752", "21755"], "wdi": "1", "mod": "g", "loc": [50.07, -103.87]}, {"id": "DPR2022-004", "et": ["v"], "wpd": "ns", "wgd": "n", "y": 2022, "bc": ["21713", "21779", "21826"], "wdi": "1", "mod": "a", "loc": [52.4, -110.02]}, {"id": "DPR2022-149", "et": ["c", "g", "v"], "wpd": "ns", "wgd": "y", "y": 2022, "bc": ["21713", "21776", "21792"], "wdi": "1", "mod": "s", "loc": [49.21, -102.07]}, {"id": "DPR2023-023", "et": ["v"], "wpd": "ns", "wgd": "n", "y": 2023, "bc": ["21903", "21711", "21743", "21903", "21708", "21720"], "wdi": "3", "mod": "ns", "loc": [50.3, -104.52]}, {"id": "DPR2023-127", "et": ["c", "g"], "wpd": "ns", "wgd": "y", "y": 2023, "bc": ["21713", "21779", "21825"], "wdi": "1", "mod": "s", "loc": [53.06, -111.28]}]}