{"meta": {"companyName": "TransMountain", "build": true, "pathTotals": [11, 11], "decimals": false, "pathFilter": [true, "radio"], "split": {"default": false}, "tollNums": [{"id": "Tariff 100", "s": "2016-05-01 00:00:00", "e": "2017-04-30 00:00:00"}, {"id": "Tariff 101", "s": "2017-05-01 00:00:00", "e": "2018-04-30 00:00:00"}, {"id": "Tariff 103", "s": "2018-05-01 00:00:00", "e": "2019-04-30 00:00:00"}, {"id": "Tariff 106", "s": "2019-05-01 00:00:00", "e": "2019-06-30 00:00:00"}, {"id": "Tariff 107", "s": "2019-07-01 00:00:00", "e": "2019-12-31 00:00:00"}, {"id": "Tariff 108", "s": "2020-01-01 00:00:00", "e": "2020-04-30 00:00:00"}, {"id": "Tariff 109", "s": "2020-05-01 00:00:00", "e": "2021-04-30 00:00:00"}, {"id": "Tariff 110", "s": "2021-05-01 00:00:00", "e": "2021-12-31 00:00:00"}, {"id": "Tariff 78", "s": "2009-01-01 00:00:00", "e": "2009-04-30 00:00:00"}, {"id": "Tariff 80", "s": "2009-05-01 00:00:00", "e": "2010-03-31 00:00:00"}, {"id": "Tariff 81", "s": "2010-04-01 00:00:00", "e": "2010-11-30 00:00:00"}, {"id": "Tariff 83", "s": "2010-12-01 00:00:00", "e": "2011-04-30 00:00:00"}, {"id": "Tariff 85", "s": "2011-05-01 00:00:00", "e": "2012-04-30 00:00:00"}, {"id": "Tariff 87", "s": "2012-05-01 00:00:00", "e": "2013-04-30 00:00:00"}, {"id": "Tariff 90", "s": "2013-05-01 00:00:00", "e": "2013-07-15 00:00:00"}, {"id": "Tariff 91", "s": "2013-07-16 00:00:00", "e": "2014-04-30 00:00:00"}, {"id": "Tariff 93", "s": "2014-05-01 00:00:00", "e": "2014-12-31 00:00:00"}, {"id": "Tariff 94", "s": "2015-01-01 00:00:00", "e": "2015-04-30 00:00:00"}, {"id": "Tariff 96", "s": "2015-05-01 00:00:00", "e": "2015-05-31 00:00:00"}, {"id": "Tariff 97", "s": "2015-06-01 00:00:00", "e": "2015-10-31 00:00:00"}, {"id": "Tariff 98", "s": "2015-11-01 00:00:00", "e": "2015-12-31 00:00:00"}, {"id": "Tariff 99", "s": "2016-01-01 00:00:00", "e": "2016-04-30 00:00:00"}], "products": false, "seriesCol": "Product", "paths": [["Edmonton-Burnaby", false], ["Edmonton-Edmonton", false], ["Edmonton-Edson", false], ["Edmonton-Kamloops", false], ["Edmonton-Sumas", false], ["Edmonton-Westridge", true], ["Edson-Burnaby", false], ["Edson-Sumas", false], ["Edson-Westridge", false], ["Kamloops-Burnaby", false], ["Kamloops-Sumas", false]], "services": [["Tank Metered, Net Toll", false]], "units": ["CN$/m3"]}, "tolls": [{"pathName": "Edmonton-Burnaby", "series": [{"id": "heavy", "p": "heavy", "s": "Tank Metered, Net Toll", "u": "CN$/m3", "data": [[[2009, 4, 1], [2010, 2, 31], 16.83], [[2010, 3, 1], [2010, 10, 30], 14.86], [[2010, 11, 1], [2011, 3, 30], 14.86], [[2011, 4, 1], [2012, 3, 30], 20.04]]}, {"id": "light", "p": "light", "s": "Tank Metered, Net Toll", "u": "CN$/m3", "data": [[[2009, 4, 1], [2010, 2, 31], 14.93], [[2010, 3, 1], [2010, 10, 30], 13.23], [[2010, 11, 1], [2011, 3, 30], 13.23], [[2011, 4, 1], [2012, 3, 30], 17.74], [[2012, 4, 1], [2013, 3, 30], 17.02], [[2013, 4, 1], [2013, 6, 15], 15.72], [[2013, 6, 16], [2014, 3, 30], 15.72], [[2014, 4, 1], [2014, 11, 31], 18.21], [[2015, 0, 1], [2015, 3, 30], 18.21], [[2015, 4, 1], [2015, 4, 31], 16.72], [[2015, 5, 1], [2015, 9, 31], 16.72], [[2015, 10, 1], [2015, 11, 31], 16.72], [[2016, 0, 1], [2016, 3, 30], 16.72], [[2016, 4, 1], [2017, 3, 30], 13.85], [[2017, 4, 1], [2018, 3, 30], 17.12], [[2018, 4, 1], [2019, 3, 30], 15.68], [[2019, 4, 1], [2019, 5, 30], 20.4], [[2019, 6, 1], [2019, 11, 31], 20.4], [[2020, 0, 1], [2020, 3, 30], 20.4], [[2020, 4, 1], [2021, 3, 30], 14.12], [[2021, 4, 1], [2021, 11, 31], 19.71]]}, {"id": "medium", "p": "medium", "s": "Tank Metered, Net Toll", "u": "CN$/m3", "data": [[[2009, 4, 1], [2010, 2, 31], 15.56], [[2010, 3, 1], [2010, 10, 30], 13.78], [[2010, 11, 1], [2011, 3, 30], 13.78], [[2011, 4, 1], [2012, 3, 30], 18.5]]}, {"id": "super heavy", "p": "super heavy", "s": "Tank Metered, Net Toll", "u": "CN$/m3", "data": [[[2009, 4, 1], [2010, 2, 31], 17.47], [[2010, 3, 1], [2010, 10, 30], 15.4], [[2010, 11, 1], [2011, 3, 30], 15.4], [[2011, 4, 1], [2012, 3, 30], 20.8]]}, {"id": "super light", "p": "super light", "s": "Tank Metered, Net Toll", "u": "CN$/m3", "data": [[[2009, 4, 1], [2010, 2, 31], 14.68], [[2010, 3, 1], [2010, 10, 30], 13.02], [[2010, 11, 1], [2011, 3, 30], 13.02], [[2011, 4, 1], [2012, 3, 30], 17.43], [[2012, 4, 1], [2013, 3, 30], 16.73], [[2013, 4, 1], [2013, 6, 15], 15.46], [[2013, 6, 16], [2014, 3, 30], 15.46], [[2014, 4, 1], [2014, 11, 31], 17.91], [[2015, 0, 1], [2015, 3, 30], 17.91], [[2015, 4, 1], [2015, 4, 31], 16.45], [[2015, 5, 1], [2015, 9, 31], 16.45], [[2015, 10, 1], [2015, 11, 31], 16.45], [[2016, 0, 1], [2016, 3, 30], 16.45], [[2016, 4, 1], [2017, 3, 30], 13.62], [[2017, 4, 1], [2018, 3, 30], 16.83], [[2018, 4, 1], [2019, 3, 30], 15.43], [[2019, 4, 1], [2019, 5, 30], 20.07], [[2019, 6, 1], [2019, 11, 31], 20.07], [[2020, 0, 1], [2020, 3, 30], 20.07], [[2020, 4, 1], [2021, 3, 30], 13.9], [[2021, 4, 1], [2021, 11, 31], 19.39]]}]}, {"pathName": "Edmonton-Edmonton", "series": [{"id": "all", "p": "all", "s": "Tank Metered, Net Toll", "u": "CN$/m3", "data": [[[2010, 3, 1], [2010, 10, 30], 1.0], [[2010, 11, 1], [2011, 3, 30], 1.0], [[2011, 4, 1], [2012, 3, 30], 0.96], [[2012, 4, 1], [2013, 3, 30], 0.99]]}, {"id": "light", "p": "light", "s": "Tank Metered, Net Toll", "u": "CN$/m3", "data": [[[2009, 4, 1], [2010, 2, 31], 0.96]]}]}, {"pathName": "Edmonton-Edson", "series": [{"id": "heavy", "p": "heavy", "s": "Tank Metered, Net Toll", "u": "CN$/m3", "data": [[[2011, 4, 1], [2012, 3, 30], 4.81]]}, {"id": "light", "p": "light", "s": "Tank Metered, Net Toll", "u": "CN$/m3", "data": [[[2011, 4, 1], [2012, 3, 30], 4.35]]}, {"id": "medium", "p": "medium", "s": "Tank Metered, Net Toll", "u": "CN$/m3", "data": [[[2011, 4, 1], [2012, 3, 30], 4.5]]}, {"id": "super heavy", "p": "super heavy", "s": "Tank Metered, Net Toll", "u": "CN$/m3", "data": [[[2011, 4, 1], [2012, 3, 30], 4.96]]}, {"id": "super light", "p": "super light", "s": "Tank Metered, Net Toll", "u": "CN$/m3", "data": [[[2011, 4, 1], [2012, 3, 30], 4.29]]}]}, {"pathName": "Edmonton-Kamloops", "series": [{"id": "light", "p": "light", "s": "Tank Metered, Net Toll", "u": "CN$/m3", "data": [[[2009, 4, 1], [2010, 2, 31], 10.66], [[2010, 3, 1], [2010, 10, 30], 9.43], [[2010, 11, 1], [2011, 3, 30], 9.43], [[2011, 4, 1], [2012, 3, 30], 12.51], [[2012, 4, 1], [2013, 3, 30], 12.02], [[2013, 4, 1], [2013, 6, 15], 11.04]]}, {"id": "super light", "p": "super light", "s": "Tank Metered, Net Toll", "u": "CN$/m3", "data": [[[2009, 4, 1], [2010, 2, 31], 10.48], [[2010, 3, 1], [2010, 10, 30], 9.28], [[2010, 11, 1], [2011, 3, 30], 9.28], [[2011, 4, 1], [2012, 3, 30], 12.29], [[2012, 4, 1], [2013, 3, 30], 11.81], [[2013, 4, 1], [2013, 6, 15], 10.85], [[2013, 6, 16], [2014, 3, 30], 10.85], [[2014, 4, 1], [2014, 11, 31], 12.52], [[2015, 0, 1], [2015, 3, 30], 12.52], [[2015, 4, 1], [2015, 4, 31], 11.48], [[2015, 5, 1], [2015, 9, 31], 11.48], [[2015, 10, 1], [2015, 11, 31], 11.48], [[2016, 0, 1], [2016, 3, 30], 11.48], [[2016, 4, 1], [2017, 3, 30], 9.5], [[2017, 4, 1], [2018, 3, 30], 11.75], [[2018, 4, 1], [2019, 3, 30], 10.75], [[2019, 4, 1], [2019, 5, 30], 13.91], [[2019, 6, 1], [2019, 11, 31], 13.91], [[2020, 0, 1], [2020, 3, 30], 13.91], [[2020, 4, 1], [2021, 3, 30], 9.55], [[2021, 4, 1], [2021, 11, 31], 13.45]]}]}, {"pathName": "Edmonton-Sumas", "series": [{"id": "heavy", "p": "heavy", "s": "Tank Metered, Net Toll", "u": "CN$/m3", "data": [[[2009, 4, 1], [2010, 2, 31], 16.12], [[2010, 3, 1], [2010, 10, 30], 14.23], [[2010, 11, 1], [2011, 3, 30], 14.23], [[2011, 4, 1], [2012, 3, 30], 19.18], [[2012, 4, 1], [2013, 3, 30], 18.36], [[2013, 4, 1], [2013, 6, 15], 16.91], [[2013, 6, 16], [2014, 3, 30], 16.91], [[2014, 4, 1], [2014, 11, 31], 19.62], [[2015, 0, 1], [2015, 3, 30], 19.62], [[2015, 4, 1], [2015, 4, 31], 17.97], [[2015, 5, 1], [2015, 9, 31], 17.97], [[2015, 10, 1], [2015, 11, 31], 17.97], [[2016, 0, 1], [2016, 3, 30], 17.97], [[2016, 4, 1], [2017, 3, 30], 14.85], [[2017, 4, 1], [2018, 3, 30], 18.41], [[2018, 4, 1], [2019, 3, 30], 16.84], [[2019, 4, 1], [2019, 5, 30], 21.93], [[2019, 6, 1], [2019, 11, 31], 21.93], [[2020, 0, 1], [2020, 3, 30], 21.93], [[2020, 4, 1], [2021, 3, 30], 15.03], [[2021, 4, 1], [2021, 11, 31], 21.14]]}, {"id": "light", "p": "light", "s": "Tank Metered, Net Toll", "u": "CN$/m3", "data": [[[2009, 4, 1], [2010, 2, 31], 14.31], [[2010, 3, 1], [2010, 10, 30], 12.68], [[2010, 11, 1], [2011, 3, 30], 12.68], [[2011, 4, 1], [2012, 3, 30], 16.98], [[2012, 4, 1], [2013, 3, 30], 16.28], [[2013, 4, 1], [2013, 6, 15], 15.04], [[2013, 6, 16], [2014, 3, 30], 15.04], [[2014, 4, 1], [2014, 11, 31], 17.43], [[2015, 0, 1], [2015, 3, 30], 17.43], [[2015, 4, 1], [2015, 4, 31], 16.01], [[2015, 5, 1], [2015, 9, 31], 16.01], [[2015, 10, 1], [2015, 11, 31], 16.01], [[2016, 0, 1], [2016, 3, 30], 16.01], [[2016, 4, 1], [2017, 3, 30], 13.24], [[2017, 4, 1], [2018, 3, 30], 16.36], [[2018, 4, 1], [2019, 3, 30], 15.0], [[2019, 4, 1], [2019, 5, 30], 19.53], [[2019, 6, 1], [2019, 11, 31], 19.53], [[2020, 0, 1], [2020, 3, 30], 19.53], [[2020, 4, 1], [2021, 3, 30], 13.51], [[2021, 4, 1], [2021, 11, 31], 18.85]]}, {"id": "medium", "p": "medium", "s": "Tank Metered, Net Toll", "u": "CN$/m3", "data": [[[2009, 4, 1], [2010, 2, 31], 14.91], [[2010, 3, 1], [2010, 10, 30], 13.2], [[2010, 11, 1], [2011, 3, 30], 13.2], [[2011, 4, 1], [2012, 3, 30], 17.71], [[2012, 4, 1], [2013, 3, 30], 16.97], [[2013, 4, 1], [2013, 6, 15], 15.67], [[2013, 6, 16], [2014, 3, 30], 15.67], [[2014, 4, 1], [2014, 11, 31], 18.16], [[2015, 0, 1], [2015, 3, 30], 18.16], [[2015, 4, 1], [2015, 4, 31], 16.67], [[2015, 5, 1], [2015, 9, 31], 16.67], [[2015, 10, 1], [2015, 11, 31], 16.67], [[2016, 0, 1], [2016, 3, 30], 16.67], [[2016, 4, 1], [2017, 3, 30], 13.78], [[2017, 4, 1], [2018, 3, 30], 17.04], [[2018, 4, 1], [2019, 3, 30], 15.61], [[2019, 4, 1], [2019, 5, 30], 20.33], [[2019, 6, 1], [2019, 11, 31], 20.33], [[2020, 0, 1], [2020, 3, 30], 20.33], [[2020, 4, 1], [2021, 3, 30], 14.02], [[2021, 4, 1], [2021, 11, 31], 19.61]]}, {"id": "super heavy", "p": "super heavy", "s": "Tank Metered, Net Toll", "u": "CN$/m3", "data": [[[2009, 4, 1], [2010, 2, 31], 16.73], [[2010, 3, 1], [2010, 10, 30], 14.75], [[2010, 11, 1], [2011, 3, 30], 14.75], [[2011, 4, 1], [2012, 3, 30], 19.91], [[2012, 4, 1], [2013, 3, 30], 19.05], [[2013, 4, 1], [2013, 6, 15], 17.53], [[2013, 6, 16], [2014, 3, 30], 17.53], [[2014, 4, 1], [2014, 11, 31], 20.35], [[2015, 0, 1], [2015, 3, 30], 20.35], [[2015, 4, 1], [2015, 4, 31], 18.62], [[2015, 5, 1], [2015, 9, 31], 18.62], [[2015, 10, 1], [2015, 11, 31], 18.62], [[2016, 0, 1], [2016, 3, 30], 18.62], [[2016, 4, 1], [2017, 3, 30], 15.38], [[2017, 4, 1], [2018, 3, 30], 19.09], [[2018, 4, 1], [2019, 3, 30], 17.45], [[2019, 4, 1], [2019, 5, 30], 22.73], [[2019, 6, 1], [2019, 11, 31], 22.73], [[2020, 0, 1], [2020, 3, 30], 22.73], [[2020, 4, 1], [2021, 3, 30], 15.53], [[2021, 4, 1], [2021, 11, 31], 21.9]]}]}, {"pathName": "Edmonton-Westridge", "series": [{"id": "heavy", "p": "heavy", "s": "Tank Metered, Net Toll", "u": "CN$/m3", "data": [[[2009, 4, 1], [2010, 2, 31], 17.41], [[2010, 3, 1], [2010, 10, 30], 15.38], [[2010, 11, 1], [2011, 3, 30], 15.38], [[2011, 4, 1], [2012, 3, 30], 21.12], [[2012, 4, 1], [2013, 3, 30], 20.38], [[2013, 4, 1], [2013, 6, 15], 18.8], [[2013, 6, 16], [2014, 3, 30], 18.8], [[2014, 4, 1], [2014, 11, 31], 21.98], [[2015, 0, 1], [2015, 3, 30], 21.98], [[2015, 4, 1], [2015, 4, 31], 20.26], [[2015, 5, 1], [2015, 9, 31], 20.26], [[2015, 10, 1], [2015, 11, 31], 20.26], [[2016, 0, 1], [2016, 3, 30], 20.26], [[2016, 4, 1], [2017, 3, 30], 18.68], [[2017, 4, 1], [2018, 3, 30], 22.49], [[2018, 4, 1], [2019, 3, 30], 19.15], [[2019, 4, 1], [2019, 5, 30], 25.32], [[2019, 6, 1], [2019, 11, 31], 25.32], [[2020, 0, 1], [2020, 3, 30], 25.32], [[2020, 4, 1], [2021, 3, 30], 17.91], [[2021, 4, 1], [2021, 11, 31], 24.93]]}, {"id": "light", "p": "light", "s": "Tank Metered, Net Toll", "u": "CN$/m3", "data": [[[2009, 4, 1], [2010, 2, 31], 15.5], [[2010, 3, 1], [2010, 10, 30], 13.74], [[2010, 11, 1], [2011, 3, 30], 13.74], [[2011, 4, 1], [2012, 3, 30], 18.82], [[2012, 4, 1], [2013, 3, 30], 18.2], [[2013, 4, 1], [2013, 6, 15], 16.84], [[2013, 6, 16], [2014, 3, 30], 16.84], [[2014, 4, 1], [2014, 11, 31], 19.67], [[2015, 0, 1], [2015, 3, 30], 19.67], [[2015, 4, 1], [2015, 4, 31], 18.2], [[2015, 5, 1], [2015, 9, 31], 18.2], [[2015, 10, 1], [2015, 11, 31], 18.2], [[2016, 0, 1], [2016, 3, 30], 18.2], [[2016, 4, 1], [2017, 3, 30], 16.99], [[2017, 4, 1], [2018, 3, 30], 20.34], [[2018, 4, 1], [2019, 3, 30], 17.22], [[2019, 4, 1], [2019, 5, 30], 22.79], [[2019, 6, 1], [2019, 11, 31], 22.79], [[2020, 0, 1], [2020, 3, 30], 22.79], [[2020, 4, 1], [2021, 3, 30], 16.32], [[2021, 4, 1], [2021, 11, 31], 22.52]]}, {"id": "medium", "p": "medium", "s": "Tank Metered, Net Toll", "u": "CN$/m3", "data": [[[2009, 4, 1], [2010, 2, 31], 16.14], [[2010, 3, 1], [2010, 10, 30], 14.29], [[2010, 11, 1], [2011, 3, 30], 14.29], [[2011, 4, 1], [2012, 3, 30], 19.59], [[2012, 4, 1], [2013, 3, 30], 18.93], [[2013, 4, 1], [2013, 6, 15], 17.49], [[2013, 6, 16], [2014, 3, 30], 17.49], [[2014, 4, 1], [2014, 11, 31], 20.44], [[2015, 0, 1], [2015, 3, 30], 20.44], [[2015, 4, 1], [2015, 4, 31], 18.88], [[2015, 5, 1], [2015, 9, 31], 18.88], [[2015, 10, 1], [2015, 11, 31], 18.88], [[2016, 0, 1], [2016, 3, 30], 18.88], [[2016, 4, 1], [2017, 3, 30], 17.55], [[2017, 4, 1], [2018, 3, 30], 21.06], [[2018, 4, 1], [2019, 3, 30], 17.86], [[2019, 4, 1], [2019, 5, 30], 23.63], [[2019, 6, 1], [2019, 11, 31], 23.63], [[2020, 0, 1], [2020, 3, 30], 23.63], [[2020, 4, 1], [2021, 3, 30], 16.85], [[2021, 4, 1], [2021, 11, 31], 23.33]]}, {"id": "super heavy", "p": "super heavy", "s": "Tank Metered, Net Toll", "u": "CN$/m3", "data": [[[2009, 4, 1], [2010, 2, 31], 18.04], [[2010, 3, 1], [2010, 10, 30], 15.92], [[2010, 11, 1], [2011, 3, 30], 15.92], [[2011, 4, 1], [2012, 3, 30], 21.89], [[2012, 4, 1], [2013, 3, 30], 21.11], [[2013, 4, 1], [2013, 6, 15], 19.46], [[2013, 6, 16], [2014, 3, 30], 19.46], [[2014, 4, 1], [2014, 11, 31], 22.74], [[2015, 0, 1], [2015, 3, 30], 22.74], [[2015, 4, 1], [2015, 4, 31], 20.94], [[2015, 5, 1], [2015, 9, 31], 20.94], [[2015, 10, 1], [2015, 11, 31], 20.94], [[2016, 0, 1], [2016, 3, 30], 20.94], [[2016, 4, 1], [2017, 3, 30], 19.24], [[2017, 4, 1], [2018, 3, 30], 23.21], [[2018, 4, 1], [2019, 3, 30], 19.8], [[2019, 4, 1], [2019, 5, 30], 26.16], [[2019, 6, 1], [2019, 11, 31], 26.16], [[2020, 0, 1], [2020, 3, 30], 26.16], [[2020, 4, 1], [2021, 3, 30], 18.45], [[2021, 4, 1], [2021, 11, 31], 25.74]]}]}, {"pathName": "Edson-Burnaby", "series": [{"id": "heavy", "p": "heavy", "s": "Tank Metered, Net Toll", "u": "CN$/m3", "data": [[[2009, 4, 1], [2010, 2, 31], 13.93], [[2010, 3, 1], [2010, 10, 30], 12.38], [[2010, 11, 1], [2011, 3, 30], 12.38]]}, {"id": "light", "p": "light", "s": "Tank Metered, Net Toll", "u": "CN$/m3", "data": [[[2009, 4, 1], [2010, 2, 31], 12.4], [[2010, 3, 1], [2010, 10, 30], 11.07], [[2010, 11, 1], [2011, 3, 30], 11.07]]}, {"id": "medium", "p": "medium", "s": "Tank Metered, Net Toll", "u": "CN$/m3", "data": [[[2009, 4, 1], [2010, 2, 31], 12.91], [[2010, 3, 1], [2010, 10, 30], 11.51], [[2010, 11, 1], [2011, 3, 30], 11.51]]}]}, {"pathName": "Edson-Sumas", "series": [{"id": "heavy", "p": "heavy", "s": "Tank Metered, Net Toll", "u": "CN$/m3", "data": [[[2009, 4, 1], [2010, 2, 31], 13.22], [[2010, 3, 1], [2010, 10, 30], 11.75], [[2010, 11, 1], [2011, 3, 30], 11.75]]}, {"id": "light", "p": "light", "s": "Tank Metered, Net Toll", "u": "CN$/m3", "data": [[[2009, 4, 1], [2010, 2, 31], 11.78], [[2010, 3, 1], [2010, 10, 30], 10.52], [[2010, 11, 1], [2011, 3, 30], 10.52]]}, {"id": "medium", "p": "medium", "s": "Tank Metered, Net Toll", "u": "CN$/m3", "data": [[[2009, 4, 1], [2010, 2, 31], 12.26], [[2010, 3, 1], [2010, 10, 30], 10.93], [[2010, 11, 1], [2011, 3, 30], 10.93]]}]}, {"pathName": "Edson-Westridge", "series": [{"id": "heavy", "p": "heavy", "s": "Tank Metered, Net Toll", "u": "CN$/m3", "data": [[[2009, 4, 1], [2010, 2, 31], 14.51], [[2010, 3, 1], [2010, 10, 30], 12.89], [[2010, 11, 1], [2011, 3, 30], 12.89]]}, {"id": "light", "p": "light", "s": "Tank Metered, Net Toll", "u": "CN$/m3", "data": [[[2009, 4, 1], [2010, 2, 31], 12.98], [[2010, 3, 1], [2010, 10, 30], 11.58], [[2010, 11, 1], [2011, 3, 30], 11.58]]}, {"id": "medium", "p": "medium", "s": "Tank Metered, Net Toll", "u": "CN$/m3", "data": [[[2009, 4, 1], [2010, 2, 31], 13.49], [[2010, 3, 1], [2010, 10, 30], 12.02], [[2010, 11, 1], [2011, 3, 30], 12.02]]}]}, {"pathName": "Kamloops-Burnaby", "series": [{"id": "light", "p": "light", "s": "Tank Metered, Net Toll", "u": "CN$/m3", "data": [[[2009, 4, 1], [2010, 2, 31], 5.61], [[2010, 3, 1], [2010, 10, 30], 5.22], [[2010, 11, 1], [2011, 3, 30], 5.22], [[2011, 4, 1], [2012, 3, 30], 6.55], [[2012, 4, 1], [2013, 3, 30], 6.39], [[2013, 4, 1], [2013, 6, 15], 6.18], [[2013, 6, 16], [2014, 3, 30], 6.18], [[2014, 4, 1], [2014, 11, 31], 7.03], [[2015, 0, 1], [2015, 3, 30], 7.03], [[2015, 4, 1], [2015, 4, 31], 6.72], [[2015, 5, 1], [2015, 9, 31], 6.72], [[2015, 10, 1], [2015, 11, 31], 6.72], [[2016, 0, 1], [2016, 3, 30], 6.72], [[2016, 4, 1], [2017, 3, 30], 5.66], [[2017, 4, 1], [2018, 3, 30], 6.68], [[2018, 4, 1], [2019, 3, 30], 6.31], [[2019, 4, 1], [2019, 5, 30], 8.17], [[2019, 6, 1], [2019, 11, 31], 8.17], [[2020, 0, 1], [2020, 3, 30], 8.17], [[2020, 4, 1], [2021, 3, 30], 6.34], [[2021, 4, 1], [2021, 11, 31], 8.06]]}]}, {"pathName": "Kamloops-Sumas", "series": [{"id": "heavy", "p": "heavy", "s": "Tank Metered, Net Toll", "u": "CN$/m3", "data": [[[2013, 6, 16], [2014, 3, 30], 5.97], [[2014, 4, 1], [2014, 11, 31], 6.79], [[2015, 0, 1], [2015, 3, 30], 6.79], [[2015, 4, 1], [2015, 4, 31], 6.49], [[2015, 5, 1], [2015, 9, 31], 6.49], [[2015, 10, 1], [2015, 11, 31], 6.49], [[2016, 0, 1], [2016, 3, 30], 6.49], [[2016, 4, 1], [2017, 3, 30], 5.46], [[2017, 4, 1], [2018, 3, 30], 6.43], [[2018, 4, 1], [2019, 3, 30], 6.09], [[2019, 4, 1], [2019, 5, 30], 7.89], [[2019, 6, 1], [2019, 11, 31], 7.89], [[2020, 0, 1], [2020, 3, 30], 7.89], [[2020, 4, 1], [2021, 3, 30], 6.12], [[2021, 4, 1], [2021, 11, 31], 7.76]]}, {"id": "light", "p": "light", "s": "Tank Metered, Net Toll", "u": "CN$/m3", "data": [[[2009, 4, 1], [2010, 2, 31], 4.99], [[2010, 3, 1], [2010, 10, 30], 4.67], [[2010, 11, 1], [2011, 3, 30], 4.67], [[2011, 4, 1], [2012, 3, 30], 5.8], [[2012, 4, 1], [2013, 3, 30], 5.65], [[2013, 4, 1], [2013, 6, 15], 5.51], [[2013, 6, 16], [2014, 3, 30], 5.51], [[2014, 4, 1], [2014, 11, 31], 6.25], [[2015, 0, 1], [2015, 3, 30], 6.25], [[2015, 4, 1], [2015, 4, 31], 6.01], [[2015, 5, 1], [2015, 9, 31], 6.01], [[2015, 10, 1], [2015, 11, 31], 6.01], [[2016, 0, 1], [2016, 3, 30], 6.01], [[2016, 4, 1], [2017, 3, 30], 5.06], [[2017, 4, 1], [2018, 3, 30], 5.92], [[2018, 4, 1], [2019, 3, 30], 5.63], [[2019, 4, 1], [2019, 5, 30], 7.29], [[2019, 6, 1], [2019, 11, 31], 7.29], [[2020, 0, 1], [2020, 3, 30], 7.29], [[2020, 4, 1], [2021, 3, 30], 5.74], [[2021, 4, 1], [2021, 11, 31], 7.19]]}, {"id": "medium", "p": "medium", "s": "Tank Metered, Net Toll", "u": "CN$/m3", "data": [[[2013, 6, 16], [2014, 3, 30], 5.66], [[2014, 4, 1], [2014, 11, 31], 6.43], [[2015, 0, 1], [2015, 3, 30], 6.43], [[2015, 4, 1], [2015, 4, 31], 6.17], [[2015, 5, 1], [2015, 9, 31], 6.17], [[2015, 10, 1], [2015, 11, 31], 6.17], [[2016, 0, 1], [2016, 3, 30], 6.17], [[2016, 4, 1], [2017, 3, 30], 5.19], [[2017, 4, 1], [2018, 3, 30], 6.09], [[2018, 4, 1], [2019, 3, 30], 5.78], [[2019, 4, 1], [2019, 5, 30], 7.49], [[2019, 6, 1], [2019, 11, 31], 7.49], [[2020, 0, 1], [2020, 3, 30], 7.49], [[2020, 4, 1], [2021, 3, 30], 5.87], [[2021, 4, 1], [2021, 11, 31], 7.38]]}]}]}